INSTALL
LICENSE
MANIFEST.in
README.md
README.rst
TODO
example.cfg
netFetchDelete
netFetchGet
netFetchPut
requirements.txt
setup.py
NetFetch/__init__.py
NetFetch/client_utils.py
NetFetch/config.py
NetFetch.egg-info/PKG-INFO
NetFetch.egg-info/SOURCES.txt
NetFetch.egg-info/dependency_links.txt
NetFetch.egg-info/requires.txt
NetFetch.egg-info/top_level.txt
doc/NetFetch.client_utils.html
doc/NetFetch.config.html
doc/NetFetch.html
doc/index.html