Metadata-Version: 1.1
Name: NetFetch
Version: 3.0.3
Summary: Networked file storage and retrieval with optional password protection and compression using Redis
Home-page: https://github.com/kata198/NetFetch
Author: Tim Savannah
Author-email: kata198@gmail.com
License: GPLv3
Keywords: NetFetch,redis,file,storage,retrieval,put,get, network,password,encrypt,netFetchPut,netFetchGet,server
Platform: UNKNOWN
Classifier: Development Status :: 5 - Production/Stable
Classifier: Programming Language :: Python
Classifier: License :: OSI Approved :: GNU General Public License v3 (GPLv3)
Classifier: Environment :: Console
Classifier: Topic :: System :: Networking
Classifier: Topic :: System :: Archiving
Classifier: Topic :: Database
Classifier: Topic :: Software Development :: Libraries :: Python Modules
Classifier: Topic :: Utilities
Classifier: Programming Language :: Python :: 2
Classifier: Programming Language :: Python :: 2
Classifier: Programming Language :: Python :: 2.6
Classifier: Programming Language :: Python :: 2.7
Classifier: Programming Language :: Python :: 3
Classifier: Programming Language :: Python :: 3.3
Classifier: Programming Language :: Python :: 3.4
Classifier: Programming Language :: Python :: 3.5
Classifier: Programming Language :: Python :: 3.6
Requires: IndexedRedis
Requires: cryptography
